{
    "song_title": "I've Seen Them All",
    "artist": "Grateful Dead",
    "num_versions_processed": 3,
    "average_features": {
        "lowlevel.loudness_ebu128.short_term.dvar2": 0.023801953842242558,
        "lowlevel.loudness_ebu128.momentary.var": 12.125997622807821,
        "lowlevel.loudness_ebu128.momentary.min": -30.056048075358074,
        "lowlevel.spectral_centroid.dvar": 59626.520833333336,
        "rhythm.beats_loudness.min": 0.0006001302075067846,
        "lowlevel.spectral_centroid.mean": 910.681396484375,
        "rhythm.beats_loudness.dvar": 0.0007146357432551061,
        "rhythm.bpm_histogram_first_peak_bpm": 119.0,
        "rhythm.beats_loudness.median": 0.05360037088394165,
        "lowlevel.loudness_ebu128.integrated": -11.676400502522787,
        "lowlevel.loudness_ebu128.short_term.mean": -12.19822883605957,
        "rhythm.beats_loudness.dmean2": 0.04018153312305609,
        "lowlevel.loudness_ebu128.momentary.dvar2": 0.3444058696428935,
        "rhythm.bpm_histogram_second_peak_weight": 0.05754971752564112,
        "lowlevel.loudness_ebu128.loudness_range": 3.666327476501465,
        "rhythm.bpm_histogram_second_peak_bpm": 125.0,
        "lowlevel.loudness_ebu128.short_term.min": -26.271868387858074,
        "lowlevel.loudness_ebu128.short_term.stdev": 2.578427314758301,
        "lowlevel.loudness_ebu128.short_term.dmean2": 0.06502923741936684,
        "lowlevel.loudness_ebu128.short_term.var": 7.7131844361623125,
        "rhythm.beats_loudness.mean": 0.055099161341786385,
        "lowlevel.spectral_centroid.max": 6889.783528645833,
        "lowlevel.loudness_ebu128.momentary.dvar": 0.24514993528525034,
        "rhythm.beats_loudness.stdev": 0.034628501161932945,
        "lowlevel.loudness_ebu128.momentary.max": -8.318328857421875,
        "lowlevel.spectral_centroid.median": 728.7288004557291,
        "lowlevel.loudness_ebu128.momentary.dmean": 0.4060579737027486,
        "lowlevel.loudness_ebu128.short_term.dvar": 0.020748553331941366,
        "rhythm.beats_loudness.var": 0.0014502607033743213,
        "lowlevel.loudness_ebu128.momentary.stdev": 3.24467925230662,
        "lowlevel.loudness_ebu128.momentary.mean": -12.424141883850098,
        "rhythm.beats_loudness.dmean": 0.022765045054256916,
        "lowlevel.average_loudness": 0.8647459745407104,
        "lowlevel.loudness_ebu128.short_term.median": -11.510540962219238,
        "rhythm.beats_loudness.max": 0.22111733754475912,
        "metadata.audio_properties.analysis.equal_loudness": 0.0,
        "lowlevel.loudness_ebu128.momentary.dmean2": 0.4903081754843394,
        "lowlevel.spectral_centroid.dvar2": 122852.3515625,
        "lowlevel.loudness_ebu128.short_term.max": -9.454442660013834,
        "lowlevel.spectral_centroid.var": 408392.5026041667,
        "rhythm.bpm_histogram_first_peak_weight": 0.39890501896540326,
        "lowlevel.loudness_ebu128.momentary.median": -11.722989082336426,
        "rhythm.bpm": 118.30070495605469,
        "rhythm.beats_loudness.dvar2": 0.0022400558615724244,
        "lowlevel.loudness_ebu128.short_term.dmean": 0.06764329473177592,
        "lowlevel.spectral_centroid.stdev": 608.4353230794271,
        "lowlevel.spectral_centroid.dmean": 173.33580525716147,
        "lowlevel.spectral_centroid.dmean2": 264.3737436930339,
        "rhythm.danceability": 1.1896718541781108,
        "lowlevel.spectral_centroid.min": 159.4896240234375,
        "rhythm.bpm_histogram_second_peak_spread": 0.3994949460029602
    },
    "outlier_flag": true,
    "outlier_reasons": [
        "Danceability Variance: 0.52 (limit 0.4)"
    ],
    "raw_versions": [
        {
            "id": "-q1sEZo7ezw",
            "title": "Bjork - I've Seen It All (Live at Oscar 2000)",
            "views": 93802,
            "features": {
                "lowlevel.average_loudness": 0.8319424986839294,
                "lowlevel.loudness_ebu128.integrated": -15.555243492126465,
                "lowlevel.loudness_ebu128.loudness_range": 6.528253555297852,
                "lowlevel.loudness_ebu128.momentary.dmean": 0.3904142379760742,
                "lowlevel.loudness_ebu128.momentary.dmean2": 0.34326884150505066,
                "lowlevel.loudness_ebu128.momentary.dvar": 0.14929576218128204,
                "lowlevel.loudness_ebu128.momentary.dvar2": 0.1336301565170288,
                "lowlevel.loudness_ebu128.momentary.max": -11.79806137084961,
                "lowlevel.loudness_ebu128.momentary.mean": -16.35451889038086,
                "lowlevel.loudness_ebu128.momentary.median": -15.79886245727539,
                "lowlevel.loudness_ebu128.momentary.min": -25.113645553588867,
                "lowlevel.loudness_ebu128.momentary.stdev": 2.860625743865967,
                "lowlevel.loudness_ebu128.momentary.var": 8.18317985534668,
                "lowlevel.loudness_ebu128.short_term.dmean": 0.07269620150327682,
                "lowlevel.loudness_ebu128.short_term.dmean2": 0.04573113098740578,
                "lowlevel.loudness_ebu128.short_term.dvar": 0.004601722117513418,
                "lowlevel.loudness_ebu128.short_term.dvar2": 0.001963593065738678,
                "lowlevel.loudness_ebu128.short_term.max": -12.644516944885254,
                "lowlevel.loudness_ebu128.short_term.mean": -16.163694381713867,
                "lowlevel.loudness_ebu128.short_term.median": -15.175044059753418,
                "lowlevel.loudness_ebu128.short_term.min": -23.189451217651367,
                "lowlevel.loudness_ebu128.short_term.stdev": 2.480400800704956,
                "lowlevel.loudness_ebu128.short_term.var": 6.152387619018555,
                "lowlevel.spectral_centroid.dmean": 198.43124389648438,
                "lowlevel.spectral_centroid.dmean2": 301.4092102050781,
                "lowlevel.spectral_centroid.dvar": 85088.265625,
                "lowlevel.spectral_centroid.dvar2": 157426.265625,
                "lowlevel.spectral_centroid.max": 11380.869140625,
                "lowlevel.spectral_centroid.mean": 1245.3631591796875,
                "lowlevel.spectral_centroid.median": 999.791259765625,
                "lowlevel.spectral_centroid.min": 220.2273712158203,
                "lowlevel.spectral_centroid.stdev": 820.123291015625,
                "lowlevel.spectral_centroid.var": 672602.1875,
                "metadata.audio_properties.analysis.equal_loudness": 0.0,
                "rhythm.beats_loudness.dmean": 0.010697639547288418,
                "rhythm.beats_loudness.dmean2": 0.018106332048773766,
                "rhythm.beats_loudness.dvar": 0.00013001768093090504,
                "rhythm.beats_loudness.dvar2": 0.0003952814731746912,
                "rhythm.beats_loudness.max": 0.07545199990272522,
                "rhythm.beats_loudness.mean": 0.0232295673340559,
                "rhythm.beats_loudness.median": 0.019154969602823257,
                "rhythm.beats_loudness.min": 0.0010933491867035627,
                "rhythm.beats_loudness.stdev": 0.015463793650269508,
                "rhythm.beats_loudness.var": 0.00023912891629152,
                "rhythm.bpm": 146.6617431640625,
                "rhythm.bpm_histogram_first_peak_bpm": 148.0,
                "rhythm.bpm_histogram_first_peak_weight": 0.5060975551605225,
                "rhythm.bpm_histogram_second_peak_bpm": 136.0,
                "rhythm.bpm_histogram_second_peak_spread": 0.6000000238418579,
                "rhythm.bpm_histogram_second_peak_weight": 0.10218977928161621,
                "rhythm.danceability": 0.9502155184745789
            }
        },
        {
            "id": "Rp0gx8CfjRA",
            "title": "Schiller And Maya Saban - I've Seen It All (live)",
            "views": 3324057,
            "features": {
                "lowlevel.average_loudness": 0.9387055039405823,
                "lowlevel.loudness_ebu128.integrated": -9.5462064743042,
                "lowlevel.loudness_ebu128.loudness_range": 2.664571762084961,
                "lowlevel.loudness_ebu128.momentary.dmean": 0.4448731541633606,
                "lowlevel.loudness_ebu128.momentary.dmean2": 0.6365090012550354,
                "lowlevel.loudness_ebu128.momentary.dvar": 0.2896541953086853,
                "lowlevel.loudness_ebu128.momentary.dvar2": 0.4879079759120941,
                "lowlevel.loudness_ebu128.momentary.max": -6.974249362945557,
                "lowlevel.loudness_ebu128.momentary.mean": -9.853853225708008,
                "lowlevel.loudness_ebu128.momentary.median": -9.264041900634766,
                "lowlevel.loudness_ebu128.momentary.min": -26.529611587524414,
                "lowlevel.loudness_ebu128.momentary.stdev": 1.9246023893356323,
                "lowlevel.loudness_ebu128.momentary.var": 3.704094171524048,
                "lowlevel.loudness_ebu128.short_term.dmean": 0.060458600521087646,
                "lowlevel.loudness_ebu128.short_term.dmean2": 0.07247499376535416,
                "lowlevel.loudness_ebu128.short_term.dvar": 0.008900525979697704,
                "lowlevel.loudness_ebu128.short_term.dvar2": 0.012701548635959625,
                "lowlevel.loudness_ebu128.short_term.max": -8.53752326965332,
                "lowlevel.loudness_ebu128.short_term.mean": -9.711920738220215,
                "lowlevel.loudness_ebu128.short_term.median": -9.266294479370117,
                "lowlevel.loudness_ebu128.short_term.min": -18.466806411743164,
                "lowlevel.loudness_ebu128.short_term.stdev": 1.3664333820343018,
                "lowlevel.loudness_ebu128.short_term.var": 1.8671400547027588,
                "lowlevel.spectral_centroid.dmean": 178.95468139648438,
                "lowlevel.spectral_centroid.dmean2": 264.66229248046875,
                "lowlevel.spectral_centroid.dvar": 54075.98046875,
                "lowlevel.spectral_centroid.dvar2": 113214.953125,
                "lowlevel.spectral_centroid.max": 3886.34130859375,
                "lowlevel.spectral_centroid.mean": 924.6358642578125,
                "lowlevel.spectral_centroid.median": 737.1477661132812,
                "lowlevel.spectral_centroid.min": 141.22198486328125,
                "lowlevel.spectral_centroid.stdev": 656.505615234375,
                "lowlevel.spectral_centroid.var": 430999.625,
                "metadata.audio_properties.analysis.equal_loudness": 0.0,
                "rhythm.beats_loudness.dmean": 0.03108162246644497,
                "rhythm.beats_loudness.dmean2": 0.05753941088914871,
                "rhythm.beats_loudness.dvar": 0.0012931578094139695,
                "rhythm.beats_loudness.dvar2": 0.00433783233165741,
                "rhythm.beats_loudness.max": 0.336978554725647,
                "rhythm.beats_loudness.mean": 0.08142483979463577,
                "rhythm.beats_loudness.median": 0.08565220236778259,
                "rhythm.beats_loudness.min": 0.0006481192540377378,
                "rhythm.beats_loudness.stdev": 0.054272014647722244,
                "rhythm.beats_loudness.var": 0.002945451531559229,
                "rhythm.bpm": 100.4333267211914,
                "rhythm.bpm_histogram_first_peak_bpm": 101.0,
                "rhythm.bpm_histogram_first_peak_weight": 0.4695431590080261,
                "rhythm.bpm_histogram_second_peak_bpm": 136.0,
                "rhythm.bpm_histogram_second_peak_spread": 0.4318181872367859,
                "rhythm.bpm_histogram_second_peak_weight": 0.05081300809979439,
                "rhythm.danceability": 1.4685026407241821
            }
        },
        {
            "id": "rsnR9R49E9Y",
            "title": "Schiller - I've seen it all (live) performed by Tricia Mc Teague",
            "views": 210286,
            "features": {
                "lowlevel.average_loudness": 0.8235899209976196,
                "lowlevel.loudness_ebu128.integrated": -9.927751541137695,
                "lowlevel.loudness_ebu128.loudness_range": 1.806157112121582,
                "lowlevel.loudness_ebu128.momentary.dmean": 0.38288652896881104,
                "lowlevel.loudness_ebu128.momentary.dmean2": 0.49114668369293213,
                "lowlevel.loudness_ebu128.momentary.dvar": 0.2964998483657837,
                "lowlevel.loudness_ebu128.momentary.dvar2": 0.4116794764995575,
                "lowlevel.loudness_ebu128.momentary.max": -6.182675838470459,
                "lowlevel.loudness_ebu128.momentary.mean": -11.064053535461426,
                "lowlevel.loudness_ebu128.momentary.median": -10.106062889099121,
                "lowlevel.loudness_ebu128.momentary.min": -38.52488708496094,
                "lowlevel.loudness_ebu128.momentary.stdev": 4.948809623718262,
                "lowlevel.loudness_ebu128.momentary.var": 24.490718841552734,
                "lowlevel.loudness_ebu128.short_term.dmean": 0.06977508217096329,
                "lowlevel.loudness_ebu128.short_term.dmean2": 0.07688158750534058,
                "lowlevel.loudness_ebu128.short_term.dvar": 0.048743411898612976,
                "lowlevel.loudness_ebu128.short_term.dvar2": 0.05674071982502937,
                "lowlevel.loudness_ebu128.short_term.max": -7.18128776550293,
                "lowlevel.loudness_ebu128.short_term.mean": -10.719071388244629,
                "lowlevel.loudness_ebu128.short_term.median": -10.09028434753418,
                "lowlevel.loudness_ebu128.short_term.min": -37.15934753417969,
                "lowlevel.loudness_ebu128.short_term.stdev": 3.8884477615356445,
                "lowlevel.loudness_ebu128.short_term.var": 15.120025634765625,
                "lowlevel.spectral_centroid.dmean": 142.62149047851562,
                "lowlevel.spectral_centroid.dmean2": 227.0497283935547,
                "lowlevel.spectral_centroid.dvar": 39715.31640625,
                "lowlevel.spectral_centroid.dvar2": 97915.8359375,
                "lowlevel.spectral_centroid.max": 5402.14013671875,
                "lowlevel.spectral_centroid.mean": 562.045166015625,
                "lowlevel.spectral_centroid.median": 449.24737548828125,
                "lowlevel.spectral_centroid.min": 117.01951599121094,
                "lowlevel.spectral_centroid.stdev": 348.67706298828125,
                "lowlevel.spectral_centroid.var": 121575.6953125,
                "metadata.audio_properties.analysis.equal_loudness": 0.0,
                "rhythm.beats_loudness.dmean": 0.02651587314903736,
                "rhythm.beats_loudness.dmean2": 0.044898856431245804,
                "rhythm.beats_loudness.dvar": 0.0007207317394204438,
                "rhythm.beats_loudness.dvar2": 0.001987053779885173,
                "rhythm.beats_loudness.max": 0.25092145800590515,
                "rhythm.beats_loudness.mean": 0.06064307689666748,
                "rhythm.beats_loudness.median": 0.0559939406812191,
                "rhythm.beats_loudness.min": 5.892218177905306e-05,
                "rhythm.beats_loudness.stdev": 0.03414969518780708,
                "rhythm.beats_loudness.var": 0.0011662016622722149,
                "rhythm.bpm": 107.80704498291016,
                "rhythm.bpm_histogram_first_peak_bpm": 108.0,
                "rhythm.bpm_histogram_first_peak_weight": 0.22107434272766113,
                "rhythm.bpm_histogram_second_peak_bpm": 103.0,
                "rhythm.bpm_histogram_second_peak_spread": 0.16666662693023682,
                "rhythm.bpm_histogram_second_peak_weight": 0.01964636519551277,
                "rhythm.danceability": 1.1502974033355713
            }
        }
    ]
}