{
    "song_title": "Mason's Children",
    "artist": "Grateful Dead",
    "num_versions_processed": 3,
    "average_features": {
        "lowlevel.loudness_ebu128.momentary.dmean2": 0.7122953534126282,
        "lowlevel.loudness_ebu128.short_term.median": -15.185209274291992,
        "lowlevel.spectral_centroid.median": 1169.2368977864583,
        "rhythm.beats_loudness.var": 0.0003205936130446692,
        "rhythm.beats_loudness.dvar": 0.00023226145034035048,
        "lowlevel.loudness_ebu128.short_term.stdev": 2.2385831673940024,
        "lowlevel.loudness_ebu128.integrated": -15.036088625590006,
        "rhythm.beats_loudness.max": 0.13459548354148865,
        "lowlevel.spectral_centroid.max": 8743.755045572916,
        "lowlevel.spectral_centroid.min": 211.35252888997397,
        "lowlevel.loudness_ebu128.momentary.stdev": 3.3619987964630127,
        "rhythm.bpm": 165.58727010091147,
        "lowlevel.loudness_ebu128.loudness_range": 5.436575253804524,
        "rhythm.beats_loudness.mean": 0.028375955298542976,
        "rhythm.bpm_histogram_second_peak_weight": 0.3535965581734975,
        "metadata.audio_properties.analysis.equal_loudness": 0.0,
        "lowlevel.loudness_ebu128.short_term.var": 5.259999434153239,
        "rhythm.beats_loudness.dvar2": 0.0006912466002783427,
        "rhythm.bpm_histogram_second_peak_bpm": 167.66666666666666,
        "lowlevel.loudness_ebu128.momentary.mean": -15.982184410095215,
        "lowlevel.loudness_ebu128.short_term.max": -11.222910086313883,
        "rhythm.beats_loudness.stdev": 0.01770656742155552,
        "lowlevel.loudness_ebu128.momentary.dmean": 0.65263565381368,
        "lowlevel.spectral_centroid.mean": 1236.0794067382812,
        "lowlevel.spectral_centroid.stdev": 481.42917887369794,
        "rhythm.beats_loudness.median": 0.025930163140098255,
        "lowlevel.loudness_ebu128.short_term.dmean": 0.0943908616900444,
        "lowlevel.loudness_ebu128.short_term.dvar2": 0.009640030252436796,
        "rhythm.beats_loudness.dmean2": 0.024508376916249592,
        "lowlevel.loudness_ebu128.short_term.mean": -15.57977326711019,
        "lowlevel.loudness_ebu128.momentary.var": 11.434728622436523,
        "rhythm.beats_loudness.dmean": 0.013830485132833322,
        "lowlevel.loudness_ebu128.momentary.min": -57.966674168904625,
        "lowlevel.loudness_ebu128.momentary.dvar": 0.5658901433149973,
        "lowlevel.spectral_centroid.dmean": 195.69615681966147,
        "lowlevel.spectral_centroid.var": 241293.2578125,
        "rhythm.beats_loudness.min": 8.851325807294567e-05,
        "lowlevel.average_loudness": 0.6161023279031118,
        "lowlevel.loudness_ebu128.short_term.dmean2": 0.09382961442073186,
        "lowlevel.loudness_ebu128.short_term.min": -29.042882919311523,
        "rhythm.bpm_histogram_first_peak_bpm": 165.66666666666666,
        "lowlevel.loudness_ebu128.momentary.max": -9.060211976369223,
        "lowlevel.spectral_centroid.dmean2": 286.4046936035156,
        "rhythm.bpm_histogram_second_peak_spread": 0.050551652908325195,
        "lowlevel.loudness_ebu128.short_term.dvar": 0.010992723051458597,
        "lowlevel.loudness_ebu128.momentary.median": -15.418931325276693,
        "rhythm.danceability": 1.1828754742940266,
        "lowlevel.spectral_centroid.dvar": 49926.560546875,
        "rhythm.bpm_histogram_first_peak_weight": 0.021610995133717854,
        "lowlevel.loudness_ebu128.momentary.dvar2": 0.7164255479971567,
        "lowlevel.spectral_centroid.dvar2": 96621.640625
    },
    "outlier_flag": true,
    "outlier_reasons": [
        "BPM Variance: 24.22 (limit 20)",
        "Danceability Variance: 0.36 (limit 0.2)"
    ],
    "raw_versions": [
        {
            "id": "LUXqGzqu4jg",
            "title": "Mason's Children (Live at Fillmore East, February 13-14, 1970)",
            "views": 10529,
            "features": {
                "lowlevel.average_loudness": 0.2629566490650177,
                "lowlevel.loudness_ebu128.integrated": -15.013978004455566,
                "lowlevel.loudness_ebu128.loudness_range": 8.190912246704102,
                "lowlevel.loudness_ebu128.momentary.dmean": 0.8466081619262695,
                "lowlevel.loudness_ebu128.momentary.dmean2": 0.9151161313056946,
                "lowlevel.loudness_ebu128.momentary.dvar": 0.7679994106292725,
                "lowlevel.loudness_ebu128.momentary.dvar2": 1.0044201612472534,
                "lowlevel.loudness_ebu128.momentary.max": -7.628951072692871,
                "lowlevel.loudness_ebu128.momentary.mean": -16.54620361328125,
                "lowlevel.loudness_ebu128.momentary.median": -16.103649139404297,
                "lowlevel.loudness_ebu128.momentary.min": -31.0026912689209,
                "lowlevel.loudness_ebu128.momentary.stdev": 3.815538167953491,
                "lowlevel.loudness_ebu128.momentary.var": 14.558331489562988,
                "lowlevel.loudness_ebu128.short_term.dmean": 0.1269111931324005,
                "lowlevel.loudness_ebu128.short_term.dmean2": 0.11230404675006866,
                "lowlevel.loudness_ebu128.short_term.dvar": 0.01992402784526348,
                "lowlevel.loudness_ebu128.short_term.dvar2": 0.014342349953949451,
                "lowlevel.loudness_ebu128.short_term.max": -10.195037841796875,
                "lowlevel.loudness_ebu128.short_term.mean": -15.962821006774902,
                "lowlevel.loudness_ebu128.short_term.median": -15.630119323730469,
                "lowlevel.loudness_ebu128.short_term.min": -25.167640686035156,
                "lowlevel.loudness_ebu128.short_term.stdev": 2.936736583709717,
                "lowlevel.loudness_ebu128.short_term.var": 8.624421119689941,
                "lowlevel.spectral_centroid.dmean": 195.67945861816406,
                "lowlevel.spectral_centroid.dmean2": 276.52789306640625,
                "lowlevel.spectral_centroid.dvar": 51597.828125,
                "lowlevel.spectral_centroid.dvar2": 95401.5078125,
                "lowlevel.spectral_centroid.max": 4717.84521484375,
                "lowlevel.spectral_centroid.mean": 1087.4986572265625,
                "lowlevel.spectral_centroid.median": 977.0040283203125,
                "lowlevel.spectral_centroid.min": 259.0561828613281,
                "lowlevel.spectral_centroid.stdev": 486.46441650390625,
                "lowlevel.spectral_centroid.var": 236647.625,
                "metadata.audio_properties.analysis.equal_loudness": 0.0,
                "rhythm.beats_loudness.dmean": 0.014029907993972301,
                "rhythm.beats_loudness.dmean2": 0.025164049118757248,
                "rhythm.beats_loudness.dvar": 0.000299675710266456,
                "rhythm.beats_loudness.dvar2": 0.0009164827060885727,
                "rhythm.beats_loudness.max": 0.14307914674282074,
                "rhythm.beats_loudness.mean": 0.02130879834294319,
                "rhythm.beats_loudness.median": 0.015882713720202446,
                "rhythm.beats_loudness.min": 0.0002634232514537871,
                "rhythm.beats_loudness.stdev": 0.019796377047896385,
                "rhythm.beats_loudness.var": 0.00039189652306959033,
                "rhythm.bpm": 178.20571899414062,
                "rhythm.bpm_histogram_first_peak_bpm": 178.0,
                "rhythm.bpm_histogram_first_peak_weight": 0.0,
                "rhythm.bpm_histogram_second_peak_bpm": 185.0,
                "rhythm.bpm_histogram_second_peak_spread": 0.0,
                "rhythm.bpm_histogram_second_peak_weight": 0.3020527958869934,
                "rhythm.danceability": 1.0276823043823242
            }
        },
        {
            "id": "IdgOsyHZxX4",
            "title": "Mason's Children (Live at the Civic Auditorium in Honolulu, HI 1970 Version)",
            "views": 16366,
            "features": {
                "lowlevel.average_loudness": 0.6403141617774963,
                "lowlevel.loudness_ebu128.integrated": -11.309776306152344,
                "lowlevel.loudness_ebu128.loudness_range": 4.512742042541504,
                "lowlevel.loudness_ebu128.momentary.dmean": 0.619299590587616,
                "lowlevel.loudness_ebu128.momentary.dmean2": 0.6108953356742859,
                "lowlevel.loudness_ebu128.momentary.dvar": 0.6374639272689819,
                "lowlevel.loudness_ebu128.momentary.dvar2": 0.6912171840667725,
                "lowlevel.loudness_ebu128.momentary.max": -4.802208423614502,
                "lowlevel.loudness_ebu128.momentary.mean": -12.012701988220215,
                "lowlevel.loudness_ebu128.momentary.median": -11.435993194580078,
                "lowlevel.loudness_ebu128.momentary.min": -53.97377014160156,
                "lowlevel.loudness_ebu128.momentary.stdev": 2.9272260665893555,
                "lowlevel.loudness_ebu128.momentary.var": 8.568653106689453,
                "lowlevel.loudness_ebu128.short_term.dmean": 0.0851178765296936,
                "lowlevel.loudness_ebu128.short_term.dmean2": 0.08230219781398773,
                "lowlevel.loudness_ebu128.short_term.dvar": 0.007098970469087362,
                "lowlevel.loudness_ebu128.short_term.dvar2": 0.006943194195628166,
                "lowlevel.loudness_ebu128.short_term.max": -7.109602451324463,
                "lowlevel.loudness_ebu128.short_term.mean": -11.64809799194336,
                "lowlevel.loudness_ebu128.short_term.median": -11.268983840942383,
                "lowlevel.loudness_ebu128.short_term.min": -18.53074836730957,
                "lowlevel.loudness_ebu128.short_term.stdev": 1.8025931119918823,
                "lowlevel.loudness_ebu128.short_term.var": 3.2493419647216797,
                "lowlevel.spectral_centroid.dmean": 135.66224670410156,
                "lowlevel.spectral_centroid.dmean2": 200.02206420898438,
                "lowlevel.spectral_centroid.dvar": 26875.587890625,
                "lowlevel.spectral_centroid.dvar2": 50383.2421875,
                "lowlevel.spectral_centroid.max": 10820.439453125,
                "lowlevel.spectral_centroid.mean": 841.0714721679688,
                "lowlevel.spectral_centroid.median": 774.9481201171875,
                "lowlevel.spectral_centroid.min": 188.75584411621094,
                "lowlevel.spectral_centroid.stdev": 359.49713134765625,
                "lowlevel.spectral_centroid.var": 129238.1796875,
                "metadata.audio_properties.analysis.equal_loudness": 0.0,
                "rhythm.beats_loudness.dmean": 0.015270777978003025,
                "rhythm.beats_loudness.dmean2": 0.026970136910676956,
                "rhythm.beats_loudness.dvar": 0.0002661092730704695,
                "rhythm.beats_loudness.dvar2": 0.0007736338302493095,
                "rhythm.beats_loudness.max": 0.15308493375778198,
                "rhythm.beats_loudness.mean": 0.032788440585136414,
                "rhythm.beats_loudness.median": 0.03090011328458786,
                "rhythm.beats_loudness.min": 1.9341289316798793e-06,
                "rhythm.beats_loudness.stdev": 0.019369272515177727,
                "rhythm.beats_loudness.var": 0.0003751687181647867,
                "rhythm.bpm": 153.98106384277344,
                "rhythm.bpm_histogram_first_peak_bpm": 152.0,
                "rhythm.bpm_histogram_first_peak_weight": 0.06483298540115356,
                "rhythm.bpm_histogram_second_peak_bpm": 157.0,
                "rhythm.bpm_histogram_second_peak_spread": 0.035164833068847656,
                "rhythm.bpm_histogram_second_peak_weight": 0.43856143951416016,
                "rhythm.danceability": 1.1374274492263794
            }
        },
        {
            "id": "xdMr_DfHNmI",
            "title": "Grateful Dead Mason\u2019s Children 12/28/69 Hollywood International Speedway (Miami Rock Festival 1969)",
            "views": 662,
            "features": {
                "lowlevel.average_loudness": 0.9450361728668213,
                "lowlevel.loudness_ebu128.integrated": -18.78451156616211,
                "lowlevel.loudness_ebu128.loudness_range": 3.6060714721679688,
                "lowlevel.loudness_ebu128.momentary.dmean": 0.49199920892715454,
                "lowlevel.loudness_ebu128.momentary.dmean2": 0.610874593257904,
                "lowlevel.loudness_ebu128.momentary.dvar": 0.29220709204673767,
                "lowlevel.loudness_ebu128.momentary.dvar2": 0.45363929867744446,
                "lowlevel.loudness_ebu128.momentary.max": -14.749476432800293,
                "lowlevel.loudness_ebu128.momentary.mean": -19.38764762878418,
                "lowlevel.loudness_ebu128.momentary.median": -18.717151641845703,
                "lowlevel.loudness_ebu128.momentary.min": -88.9235610961914,
                "lowlevel.loudness_ebu128.momentary.stdev": 3.3432321548461914,
                "lowlevel.loudness_ebu128.momentary.var": 11.177201271057129,
                "lowlevel.loudness_ebu128.short_term.dmean": 0.07114351540803909,
                "lowlevel.loudness_ebu128.short_term.dmean2": 0.08688259869813919,
                "lowlevel.loudness_ebu128.short_term.dvar": 0.005955170840024948,
                "lowlevel.loudness_ebu128.short_term.dvar2": 0.007634546607732773,
                "lowlevel.loudness_ebu128.short_term.max": -16.364089965820312,
                "lowlevel.loudness_ebu128.short_term.mean": -19.128400802612305,
                "lowlevel.loudness_ebu128.short_term.median": -18.656524658203125,
                "lowlevel.loudness_ebu128.short_term.min": -43.430259704589844,
                "lowlevel.loudness_ebu128.short_term.stdev": 1.9764198064804077,
                "lowlevel.loudness_ebu128.short_term.var": 3.9062352180480957,
                "lowlevel.spectral_centroid.dmean": 255.74676513671875,
                "lowlevel.spectral_centroid.dmean2": 382.66412353515625,
                "lowlevel.spectral_centroid.dvar": 71306.265625,
                "lowlevel.spectral_centroid.dvar2": 144080.171875,
                "lowlevel.spectral_centroid.max": 10692.98046875,
                "lowlevel.spectral_centroid.mean": 1779.6680908203125,
                "lowlevel.spectral_centroid.median": 1755.758544921875,
                "lowlevel.spectral_centroid.min": 186.2455596923828,
                "lowlevel.spectral_centroid.stdev": 598.3259887695312,
                "lowlevel.spectral_centroid.var": 357993.96875,
                "metadata.audio_properties.analysis.equal_loudness": 0.0,
                "rhythm.beats_loudness.dmean": 0.012190769426524639,
                "rhythm.beats_loudness.dmean2": 0.021390944719314575,
                "rhythm.beats_loudness.dvar": 0.0001309993676841259,
                "rhythm.beats_loudness.dvar2": 0.000383623264497146,
                "rhythm.beats_loudness.max": 0.10762237012386322,
                "rhythm.beats_loudness.mean": 0.031030626967549324,
                "rhythm.beats_loudness.median": 0.031007662415504456,
                "rhythm.beats_loudness.min": 1.8239383337004256e-07,
                "rhythm.beats_loudness.stdev": 0.013954052701592445,
                "rhythm.beats_loudness.var": 0.00019471559789963067,
                "rhythm.bpm": 164.5750274658203,
                "rhythm.bpm_histogram_first_peak_bpm": 167.0,
                "rhythm.bpm_histogram_first_peak_weight": 0.0,
                "rhythm.bpm_histogram_second_peak_bpm": 161.0,
                "rhythm.bpm_histogram_second_peak_spread": 0.11649012565612793,
                "rhythm.bpm_histogram_second_peak_weight": 0.320175439119339,
                "rhythm.danceability": 1.3835166692733765
            }
        }
    ]
}